timed_threads/__init__.py
timed_threads/signalstop.py
timed_threads/threadstop.py
timed_threads/utils.py
timed_threads/version.py
timed_threads-2.0.0.dist-info/licenses/LICENSE
timed_threads-2.0.0.dist-info/METADATA
timed_threads-2.0.0.dist-info/WHEEL
timed_threads-2.0.0.dist-info/top_level.txt
timed_threads-2.0.0.dist-info/RECORD
