Metadata-Version: 2.4
Name: Timed-Threads
Version: 2.0.0
Summary: Absolute time deadlines and thread cancelling for Python asynchronous threads
Maintainer: Mathics3 Group
License-Expression: MIT
Project-URL: Homepage, https://github.com/Mathics3/python-timed-threads/
Classifier: Topic :: Utilities
Classifier: Programming Language :: Python
Classifier: Programming Language :: Python :: Implementation :: CPython
Classifier: Programming Language :: Python :: 3.10
Classifier: Programming Language :: Python :: 3.11
Classifier: Programming Language :: Python :: 3.12
Classifier: Programming Language :: Python :: 3.13
Classifier: Programming Language :: Python :: 3.14
Classifier: Operating System :: OS Independent
Classifier: Intended Audience :: Developers
Classifier: Development Status :: 5 - Production/Stable
Requires-Python: >=3.10
License-File: LICENSE
Provides-Extra: dev
Requires-Dist: pytest; extra == "dev"
Dynamic: license-file
